pygifconvt_irealize/__init__.py
pygifconvt_irealize/converter.py
pygifconvt_irealize-1.0.1.dist-info/LICENSE
pygifconvt_irealize-1.0.1.dist-info/METADATA
pygifconvt_irealize-1.0.1.dist-info/WHEEL
pygifconvt_irealize-1.0.1.dist-info/top_level.txt
pygifconvt_irealize-1.0.1.dist-info/RECORD
