Metadata-Version: 2.1
Name: pygifconvt-irealize
Version: 1.0.1
Summary: Test package for distribution
Home-page: 
Download-URL: 
Author: irealize
Author-email: irealize@naver.com
License: UNKNOWN
Keywords: GIFCONVERTER,gifconverter,irealize
Platform: UNKNOWN
Classifier: Programming Language :: Python :: 3
Classifier: License :: OSI Approved :: MIT License
Classifier: Operating System :: OS Independent
Requires-Python: >=3
License-File: LICENSE
Requires-Dist: pillow
